EVM_final/design.sv
module evm (
    input clk,
    input rst,
    input button_bjp,
    input button_jdu,
    input button_rjd,
    input button_inc,
    input [3:0] passkey, // 4-bit passkey input
    input result_enable, // New input signal to enable result display
    output reg [7:0] bjp, jdu, rjd, inc,
    output reg led_bjp, led_jdu, led_rjd, led_inc
);
    // Define the correct passkey (adjust as needed)
    parameter correct_passkey = 4'b1010;

    // Initialize all registers to 0
    initial begin
        bjp = 0; jdu = 0; rjd = 0; inc = 0;
        led_bjp = 0; led_jdu = 0; led_rjd = 0; led_inc = 0;
    end

    // Debounce signals
    reg [1:0] db_bjp, db_jdu, db_rjd, db_inc;
    
    always @(posedge clk or posedge rst) begin
        if (rst) begin
            db_bjp <= 2'b00;
            db_jdu <= 2'b00;
            db_rjd <= 2'b00;
            db_inc <= 2'b00;
        end else begin
            db_bjp <= {db_bjp[0], button_bjp};
            db_jdu <= {db_jdu[0], button_jdu};
            db_rjd <= {db_rjd[0], button_rjd};
            db_inc <= {db_inc[0], button_inc};
        end
    end

    // Count votes based on button press
    always @(posedge clk or posedge rst) begin
        if (rst) begin
            bjp <= 0;
            jdu <= 0;
            rjd <= 0;
            inc <= 0;
        end else begin
            if (db_bjp == 2'b01) bjp <= bjp + 1;
            if (db_jdu == 2'b01) jdu <= jdu + 1;
            if (db_rjd == 2'b01) rjd <= rjd + 1;
            if (db_inc == 2'b01) inc <= inc + 1;
        end
    end

    // Determine the winner among all parties
    always @* begin
        // Reset all LEDs
        led_bjp = 0;
        led_jdu = 0;
        led_rjd = 0;
        led_inc = 0;

        // Only display the result if the passkey is correct and result_enable is high
        if (passkey == correct_passkey && result_enable) begin
            if (bjp > jdu && bjp > rjd && bjp > inc) begin
                led_bjp = 1;
            end else if (jdu > rjd && jdu > inc) begin
                led_jdu = 1;
            end else if (rjd > inc) begin
                led_rjd = 1;
            end else begin
                led_inc = 1;
            end
        end
    end
endmodule

EVM_final/design_tb.sv
`include "design.sv"
module tb_top;

    // Inputs
    reg clk;
    reg rst;
    reg button_bjp;
    reg button_jdu;
    reg button_rjd;
    reg button_inc;
    reg [3:0] passkey;
    reg result_enable;

    // Outputs
    wire [7:0] bjp;
    wire [7:0] jdu;
    wire [7:0] rjd;
    wire [7:0] inc;
    wire led_bjp;
    wire led_jdu;
    wire led_rjd;
    wire led_inc;

    // Instantiate the EVM module
    evm uut (
        .clk(clk),
        .rst(rst),
        .button_bjp(button_bjp),
        .button_jdu(button_jdu),
        .button_rjd(button_rjd),
        .button_inc(button_inc),
        .passkey(passkey),
        .result_enable(result_enable),
        .bjp(bjp),
        .jdu(jdu),
        .rjd(rjd),
        .inc(inc),
        .led_bjp(led_bjp),
        .led_jdu(led_jdu),
        .led_rjd(led_rjd),
        .led_inc(led_inc)
    );

    // Clock generation
    always begin
        #5 clk = ~clk; // Toggle clock every 5 time units
    end

    // Test sequence
    initial begin
        // Initialize inputs
        clk = 0;
        rst = 1;
        button_bjp = 0;
        button_jdu = 0;
        button_rjd = 0;
        button_inc = 0;
        passkey = 4'b0000;
        result_enable = 0;

        // Wait for global reset
        #10;
        rst = 0;

        // Simulate button presses
        #10 button_bjp = 1; #10 button_bjp = 0; // BJP gets 1 vote
        #10 button_jdu = 1; #10 button_jdu = 0; // JDU gets 1 vote
        #10 button_jdu = 1; #10 button_jdu = 0; // JDU gets 1 vote
        #10 button_jdu = 1; #10 button_jdu = 0; // JDU gets 1 vote
        #10 button_jdu = 1; #10 button_jdu = 0; // JDU gets 1 vote
        #10 button_jdu = 1; #10 button_jdu = 0; // JDU gets 1 vote
        #10 button_rjd = 1; #10 button_rjd = 0; // RJD gets 1 vote
        #10 button_inc = 1; #10 button_inc = 0; // INC gets 1 vote
        #10 button_bjp = 1; #10 button_bjp = 0; // BJP gets another vote

        // Check votes without passkey
        passkey = 4'b0000;
        result_enable = 1;
        #10;
        //$display("Without correct passkey: BJP=%d, JDU=%d, RJD=%d, INC=%d, LED_BJP=%b, LED_JDU=%b, LED_RJD=%b, LED_INC=%b",
                 bjp, jdu, rjd, inc, led_bjp, led_jdu, led_rjd, led_inc);

        // Check votes with correct passkey
        passkey = 4'b1010;
        result_enable = 1;
        #10;
        $display("With correct passkey: BJP=%d, JDU=%d, RJD=%d, INC=%d, LED_BJP=%b, LED_JDU=%b, LED_RJD=%b, LED_INC=%b",
                 bjp, jdu, rjd, inc, led_bjp, led_jdu, led_rjd, led_inc);

        // Disable result enable and check
        result_enable = 0;
        #10;
      //  $display("With correct passkey but result enable off: BJP=%d, JDU=%d, RJD=%d, INC=%d, LED_BJP=%b, LED_JDU=%b, LED_RJD=%b, LED_INC=%b",
                 bjp, jdu, rjd, inc, led_bjp, led_jdu, led_rjd, led_inc);

        // End simulation
        $stop;
    end
          initial begin
        $dumpfile("dump.vcd");
$dumpvars;
# 10000 $finish;
        end
endmodule

EVM_final/dump.vcd
$date
	Fri Jun 28 13:29:36 2024
$end
$version
	QuestaSim Version 10.6c
$end
$timescale
	1ns
$end

$scope module tb_top $end
$var reg 1 ! clk $end
$var reg 1 " rst $end
$var reg 1 # button_bjp $end
$var reg 1 $ button_jdu $end
$var reg 1 % button_rjd $end
$var reg 1 & button_inc $end
$var reg 4 ' passkey [3:0] $end
$var reg 1 ( result_enable $end
$var wire 1 ) bjp [7] $end
$var wire 1 * bjp [6] $end
$var wire 1 + bjp [5] $end
$var wire 1 , bjp [4] $end
$var wire 1 - bjp [3] $end
$var wire 1 . bjp [2] $end
$var wire 1 / bjp [1] $end
$var wire 1 0 bjp [0] $end
$var wire 1 1 jdu [7] $end
$var wire 1 2 jdu [6] $end
$var wire 1 3 jdu [5] $end
$var wire 1 4 jdu [4] $end
$var wire 1 5 jdu [3] $end
$var wire 1 6 jdu [2] $end
$var wire 1 7 jdu [1] $end
$var wire 1 8 jdu [0] $end
$var wire 1 9 rjd [7] $end
$var wire 1 : rjd [6] $end
$var wire 1 ; rjd [5] $end
$var wire 1 < rjd [4] $end
$var wire 1 = rjd [3] $end
$var wire 1 > rjd [2] $end
$var wire 1 ? rjd [1] $end
$var wire 1 @ rjd [0] $end
$var wire 1 A inc [7] $end
$var wire 1 B inc [6] $end
$var wire 1 C inc [5] $end
$var wire 1 D inc [4] $end
$var wire 1 E inc [3] $end
$var wire 1 F inc [2] $end
$var wire 1 G inc [1] $end
$var wire 1 H inc [0] $end
$var wire 1 I led_bjp $end
$var wire 1 J led_jdu $end
$var wire 1 K led_rjd $end
$var wire 1 L led_inc $end

$scope module uut $end
$var parameter 4 M correct_passkey $end
$var wire 1 N clk $end
$var wire 1 O rst $end
$var wire 1 P button_bjp $end
$var wire 1 Q button_jdu $end
$var wire 1 R button_rjd $end
$var wire 1 S button_inc $end
$var wire 1 T passkey [3] $end
$var wire 1 U passkey [2] $end
$var wire 1 V passkey [1] $end
$var wire 1 W passkey [0] $end
$var wire 1 X result_enable $end
$var reg 8 Y bjp [7:0] $end
$var reg 8 Z jdu [7:0] $end
$var reg 8 [ rjd [7:0] $end
$var reg 8 \ inc [7:0] $end
$var reg 1 ] led_bjp $end
$var reg 1 ^ led_jdu $end
$var reg 1 _ led_rjd $end
$var reg 1 ` led_inc $end
$var reg 2 a db_bjp [1:0] $end
$var reg 2 b db_jdu [1:0] $end
$var reg 2 c db_rjd [1:0] $end
$var reg 2 d db_inc [1:0] $end
$upscope $end
$upscope $end

$scope begin std $end
$upscope $end
$enddefinitions $end
#0
$dumpvars
0!
1"
0#
0$
0%
0&
b0 '
0(
b0 Y
b0 Z
b0 [
b0 \
0]
0^
0_
0`
b0 a
b0 b
b0 c
b0 d
b1010 M
00
0/
0.
0-
0,
0+
0*
0)
08
07
06
05
04
03
02
01
0@
0?
0>
0=
0<
0;
0:
09
0H
0G
0F
0E
0D
0C
0B
0A
0I
0J
0K
0L
0X
0W
0V
0U
0T
0S
0R
0Q
0P
1O
0N
$end
#5
1!
1N
#10
0"
0!
0O
0N
#15
1!
1N
#20
1#
0!
1P
0N
#25
1!
1N
b1 a
#30
0#
0!
0P
0N
#35
1!
1N
b10 a
b1 Y
10
#40
1$
0!
1Q
0N
#45
1!
1N
b0 a
b1 b
#50
0$
0!
0Q
0N
#55
1!
1N
b10 b
b1 Z
18
#60
1$
0!
1Q
0N
#65
1!
1N
b1 b
#70
0$
0!
0Q
0N
#75
1!
1N
b10 b
b10 Z
08
17
#80
1$
0!
1Q
0N
#85
1!
1N
b1 b
#90
0$
0!
0Q
0N
#95
1!
1N
b10 b
b11 Z
18
#100
1$
0!
1Q
0N
#105
1!
1N
b1 b
#110
0$
0!
0Q
0N
#115
1!
1N
b10 b
b100 Z
08
07
16
#120
1$
0!
1Q
0N
#125
1!
1N
b1 b
#130
0$
0!
0Q
0N
#135
1!
1N
b10 b
b101 Z
18
#140
1%
0!
1R
0N
#145
1!
1N
b0 b
b1 c
#150
0%
0!
0R
0N
#155
1!
1N
b10 c
b1 [
1@
#160
1&
0!
1S
0N
#165
1!
1N
b0 c
b1 d
#170
0&
0!
0S
0N
#175
1!
1N
b10 d
b1 \
1H
#180
1#
0!
1P
0N
#185
1!
1N
b1 a
b0 d
#190
0#
1(
0!
0P
1X
0N
#195
1!
1N
b10 a
b10 Y
00
1/
#200
b1010 '
0!
1V
1T
0N
1^
1J
#205
1!
1N
b0 a
#210
0(
0!
0X
0N
0^
0J
